heroku_tools/__init__.py
heroku_tools/config.py
heroku_tools/deploy.py
heroku_tools/git.py
heroku_tools/heroku.py
heroku_tools/tests.py
heroku_tools/utils.py
heroku_tools/settings/__init__.py
heroku_tools-0.3.3.dist-info/DESCRIPTION.rst
heroku_tools-0.3.3.dist-info/METADATA
heroku_tools-0.3.3.dist-info/RECORD
heroku_tools-0.3.3.dist-info/WHEEL
heroku_tools-0.3.3.dist-info/entry_points.txt
heroku_tools-0.3.3.dist-info/metadata.json
heroku_tools-0.3.3.dist-info/top_level.txt
