Metadata-Version: 2.0
Name: heroku-tools
Version: 0.3.3
Summary: Command line application for managing Heroku applications.
Home-page: https://github.com/yunojuno/heroku-tools
Author: Hugo Rodger-Brown
Author-email: hugo@yunojuno.com
License: MIT
Platform: UNKNOWN
Classifier: Development Status :: 3 - Alpha
Classifier: Environment :: Console
Classifier: Intended Audience :: Developers
Classifier: License :: OSI Approved :: MIT License
Classifier: Programming Language :: Python
Classifier: Programming Language :: Python :: 2
Requires-Dist: PyYAML (==3.12)
Requires-Dist: click (==6.6)
Requires-Dist: dateutils (==0.6.6)
Requires-Dist: mock (==2.0.0)
Requires-Dist: requests (==2.11.1)
Requires-Dist: sarge (==0.1.4)
